swarmauri_parser_bertembedding/BERTEmbeddingParser.py
swarmauri_parser_bertembedding/__init__.py
swarmauri_parser_bertembedding-0.7.5.dist-info/LICENSE
swarmauri_parser_bertembedding-0.7.5.dist-info/METADATA
swarmauri_parser_bertembedding-0.7.5.dist-info/WHEEL
swarmauri_parser_bertembedding-0.7.5.dist-info/entry_points.txt
swarmauri_parser_bertembedding-0.7.5.dist-info/RECORD
